logmd/__init__.py
logmd/auth.py
logmd/cli/auth.py
logmd/cli/main.py
logmd/constants.py
logmd/data_models.py
logmd/logmd.py
logmd/utils.py
logmd-0.1.45.dist-info/LICENSE
logmd-0.1.45.dist-info/METADATA
logmd-0.1.45.dist-info/WHEEL
logmd-0.1.45.dist-info/entry_points.txt
logmd-0.1.45.dist-info/RECORD
